badapted/__init__.py
badapted/choice_functions.py
badapted/designs.py
badapted/inference.py
badapted/model.py
badapted/optimisation.py
badapted/triplot.py
badapted/utils.py
badapted-0.0.3.dist-info/LICENSE.txt
badapted-0.0.3.dist-info/METADATA
badapted-0.0.3.dist-info/WHEEL
badapted-0.0.3.dist-info/top_level.txt
badapted-0.0.3.dist-info/RECORD
