Metadata-Version: 2.1
Name: badapted
Version: 0.0.3
Summary: Bayesian ADAPTive Experimental Design
Home-page: https://github.com/drbenvincent/badapted
Author: Benjamin T. Vincent
Author-email: b.t.vincent@dundee.ac.uk
License: UNKNOWN
Keywords: bayesian,adaptive design,inference,optimisation
Platform: UNKNOWN
Classifier: Programming Language :: Python :: 3
Classifier: License :: OSI Approved :: MIT License
Classifier: Operating System :: OS Independent
